scenario_builder/__init__.py
scenario_builder/commodity.py
scenario_builder/data.py
scenario_builder/demand.py
scenario_builder/feedin.py
scenario_builder/mobility.py
scenario_builder/powerplants.py
scenario_builder/storages.py
scenario_builder-0.0.2.dist-info/AUTHORS.rst
scenario_builder-0.0.2.dist-info/LICENSE
scenario_builder-0.0.2.dist-info/METADATA
scenario_builder-0.0.2.dist-info/WHEEL
scenario_builder-0.0.2.dist-info/top_level.txt
scenario_builder-0.0.2.dist-info/RECORD
