Metadata-Version: 2.1
Name: scenario-builder
Version: 0.0.2
Summary: Tools to build scenario inputs from historical data or future assumptions
Home-page: https://github.com/reegis/scenario_builder
Author: reegis
Author-email: krien@uni-bremen.de
License: MIT
Project-URL: Documentation, https://scenario_builder.readthedocs.io/
Project-URL: Changelog, https://scenario_builder.readthedocs.io/en/latest/changelog.html
Project-URL: Issue Tracker, https://github.com/reegis/scenario_builder/issues
Platform: UNKNOWN
Classifier: Development Status :: 4 - Beta
Classifier: Intended Audience :: Developers
Classifier: License :: OSI Approved :: MIT License
Classifier: Operating System :: Unix
Classifier: Operating System :: POSIX
Classifier: Operating System :: Microsoft :: Windows
Classifier: Programming Language :: Python
Classifier: Programming Language :: Python :: 3
Classifier: Programming Language :: Python :: 3.7
Classifier: Programming Language :: Python :: 3.8
Classifier: Programming Language :: Python :: 3.9
Classifier: Topic :: Utilities
Requires-Python: >=3.7
Requires-Dist: pandas
Provides-Extra: reegis
Requires-Dist: reegis ; extra == 'reegis'
